{
	"info": {
		"_postman_id": "ceaa4db9-4ec2-40ef-8ad2-8d500179bb6d",
		"name": "Go kit",
		"schema": "https://schema.getpostman.com/json/collection/v2.1.0/collection.json",
		"_exporter_id": "22440665"
	},
	"item": [
		{
			"name": "Wholesale",
			"request": {
				"method": "POST",
				"header": [],
				"body": {
					"mode": "raw",
					"raw": "{\"partner\":\"superstore\",\"code\":\"aaa111\",\"qty\":10}"
				},
				"url": {
					"raw": "http://localhost:8080/wholesale",
					"protocol": "http",
					"host": [
						"localhost"
					],
					"port": "8080",
					"path": [
						"wholesale"
					]
				}
			},
			"response": []
		}
	]
}